ursgal/__init__.py
ursgal/chemical_composition.py
ursgal/chemical_composition_kb.py
ursgal/profiles.py
ursgal/ucontroller.py
ursgal/ucore.py
ursgal/uinstaller.py
ursgal/ukb.py
ursgal/umapmaster.py
ursgal/unimod_mapper.py
ursgal/unode.py
ursgal/uparams.py
ursgal/version.txt
ursgal/resources/platform_independent/arc_independent/_test_node/test_node.py
ursgal/resources/platform_independent/arc_independent/add_estimated_fdr_1_0_0/add_estimated_fdr_1_0_0.py
ursgal/resources/platform_independent/arc_independent/combine_FDR_0_1/combine_FDR_0_1.py
ursgal/resources/platform_independent/arc_independent/combine_pep_1_0_0/combine_pep_1_0_0.py
ursgal/resources/platform_independent/arc_independent/csv2counted_results_1_0_0/csv2counted_results_1_0_0.py
ursgal/resources/platform_independent/arc_independent/csv2ssl_1_0_0/csv2ssl_1_0_0.py
ursgal/resources/platform_independent/arc_independent/ext/unimod.xml
ursgal/resources/platform_independent/arc_independent/filter_csv_1_0_0/filter_csv_1_0_0.py
ursgal/resources/platform_independent/arc_independent/generate_target_decoy_1_0_0/generate_target_decoy_1_0_0.py
ursgal/resources/platform_independent/arc_independent/get_ftp_files_1_0_0/get_ftp_files_1_0_0.py
ursgal/resources/platform_independent/arc_independent/get_http_files_1_0_0/get_http_files_1_0_0.py
ursgal/resources/platform_independent/arc_independent/mascot_dat2csv_1_0_0/mascot_dat2csv_1_0_0.py
ursgal/resources/platform_independent/arc_independent/merge_csvs_1_0_0/merge_csvs_1_0_0.py
ursgal/resources/platform_independent/arc_independent/mgf_to_rt_lookup_1_0_0/mgf_to_rt_lookup_1_0_0.py
ursgal/resources/platform_independent/arc_independent/msgfplus2csv_py_v1_0_0/msgfplus2csv_py_v1_0_0.py
ursgal/resources/platform_independent/arc_independent/mzml2dta_0_1_0/mzml2dta_0_1_0.py
ursgal/resources/platform_independent/arc_independent/mzml2mgf_1_0_0/mzml2mgf_1_0_0.py
ursgal/resources/platform_independent/arc_independent/mzml2mgf_2_0_0/mzml2mgf_2_0_0.py
ursgal-0.6.8.dist-info/AUTHORS.txt
ursgal-0.6.8.dist-info/COPYING.txt
ursgal-0.6.8.dist-info/LICENSE.txt
ursgal-0.6.8.dist-info/METADATA
ursgal-0.6.8.dist-info/WHEEL
ursgal-0.6.8.dist-info/entry_points.txt
ursgal-0.6.8.dist-info/top_level.txt
ursgal-0.6.8.dist-info/RECORD
