Metadata-Version: 2.1
Name: ursgal
Version: 0.6.8
Summary: ursgal
Home-page: http://ursgal.github.com
Author: Lukas P. M. Kremer, Purevdulam Oyunchimeg, Johannes Barth, Stefan Schulze and Christian Fufezan
Author-email: christian@fufezan.net
License: Lesser GNU General Public License (LGPL)
Platform: any that supports python 3.5
Classifier: Development Status :: 4 - Beta
Classifier: Environment :: Console
Classifier: Intended Audience :: Education
Classifier: Intended Audience :: Science/Research
Classifier: Intended Audience :: Developers
Classifier: Operating System :: MacOS :: MacOS X
Classifier: Operating System :: Microsoft :: Windows
Classifier: Operating System :: POSIX
Classifier: Operating System :: POSIX :: SunOS/Solaris
Classifier: Operating System :: Unix
Classifier: Programming Language :: Python :: 3
Classifier: Programming Language :: Python :: 3.5
Classifier: Topic :: Scientific/Engineering :: Bio-Informatics
Classifier: Topic :: Scientific/Engineering :: Chemistry
Classifier: Topic :: Scientific/Engineering :: Medical Science Apps.
Classifier: Topic :: Software Development :: Libraries :: Python Modules
Requires-Dist: pymzml (==2.4.6)
Requires-Dist: nose (==1.3.7)
Requires-Dist: regex
Requires-Dist: pyqms (==0.6.2)
Requires-Dist: coverage
Requires-Dist: codecov
Requires-Dist: tox
Requires-Dist: pre-commit
Requires-Dist: pyahocorasick (>=1.1.4) ; sys_platform != "win32"
